apkit_flask/__init__.py
apkit_flask/routes/inbox.py
apkit_flask/routes/nodeinfo.py
apkit_flask/routes/outbox.py
apkit_flask/types.py
apkit_flask-0.1.0.dist-info/WHEEL
apkit_flask-0.1.0.dist-info/entry_points.txt
apkit_flask-0.1.0.dist-info/METADATA
apkit_flask-0.1.0.dist-info/RECORD
